context_variables/__init__.py
django_context_variables-0.0.3.dist-info/DESCRIPTION.rst
django_context_variables-0.0.3.dist-info/METADATA
django_context_variables-0.0.3.dist-info/RECORD
django_context_variables-0.0.3.dist-info/WHEEL
django_context_variables-0.0.3.dist-info/metadata.json
django_context_variables-0.0.3.dist-info/top_level.txt
