Metadata-Version: 2.0
Name: django-context-variables
Version: 0.0.3
Summary: Simple utility to help make declarative class-based views in Django
Home-page: https://github.com/carlmjohnson/django-context-variables
Author: Carl M. Johnson
Author-email: UNKNOWN
License: MIT
Platform: UNKNOWN
Classifier: Development Status :: 5 - Production/Stable
Classifier: Environment :: Web Environment
Classifier: Intended Audience :: Developers
Classifier: License :: OSI Approved :: BSD License
Classifier: Operating System :: OS Independent
Classifier: Programming Language :: Python
Classifier: Programming Language :: Python :: 2.7
Classifier: Programming Language :: Python :: 3
Classifier: Framework :: Django
